seiko_converter/__init__.py
seiko_converter/__main__.py
seiko_converter/commons.py
seiko_converter/qt2100_converter.py
seiko_converter/qt2100_parser.py
seiko_converter-1.0.0.dist-info/LICENSE
seiko_converter-1.0.0.dist-info/METADATA
seiko_converter-1.0.0.dist-info/WHEEL
seiko_converter-1.0.0.dist-info/entry_points.txt
seiko_converter-1.0.0.dist-info/top_level.txt
seiko_converter-1.0.0.dist-info/RECORD
