Metadata-Version: 2.1
Name: seiko_converter
Version: 1.0.0
Summary: Seiko Converter is a software allowing to generate graphs based on the raw data produced by the Seiko Qt-2100 Timegrapher device.
Home-page: https://github.com/ysard/seiko_qt2100_converter
Author: Ysard
Author-email: ysard_git@gmx.fr
Keywords: printer,seiko,timegrapher,chronograph,seiko qt-2100,centronics,serial,parallel
Classifier: Development Status :: 4 - Beta
Classifier: Intended Audience :: End Users/Desktop
Classifier: Intended Audience :: System Administrators
Classifier: Programming Language :: Python :: 3
Classifier: Programming Language :: Python :: 3.8
Classifier: Programming Language :: Python :: 3.9
Classifier: Programming Language :: Python :: 3.10
Classifier: Programming Language :: Python :: 3.11
Classifier: Programming Language :: Python :: 3.12
Classifier: License :: OSI Approved :: GNU Affero General Public License v3 or later (AGPLv3+)
Requires-Python: >=3.8
License-File: LICENSE
Requires-Dist: matplotlib >=3.6.3
Requires-Dist: pandas >=2.1.4
Requires-Dist: numpy >=1.26.3
Provides-Extra: dev
Requires-Dist: pytest-cov >=2.6.1 ; extra == 'dev'
Requires-Dist: pytest-timeout ; extra == 'dev'
Requires-Dist: pytest >=6.2.0 ; extra == 'dev'
Requires-Dist: zest.releaser[recommended] ; extra == 'dev'
Requires-Dist: coverage-badge ; extra == 'dev'
Requires-Dist: prospector ; extra == 'dev'
Requires-Dist: pyroma ; extra == 'dev'
Requires-Dist: check-manifest ; extra == 'dev'
Provides-Extra: doc
Requires-Dist: sphinx ; extra == 'doc'
Requires-Dist: sphinx-rtd-theme >=1.0.0 ; extra == 'doc'
Requires-Dist: sphinxcontrib-mermaid ; extra == 'doc'
Requires-Dist: sphinx-argparse ; extra == 'doc'
